speckle2graph/__init__.py
speckle2graph/interfaces.py
speckle2graph/pipeline.py
speckle2graph/graph_builders/__init__.py
speckle2graph/graph_builders/graph_builders.py
speckle2graph/graph_builders/node_property_extractors.py
speckle2graph/models/__init__.py
speckle2graph/models/geometry.py
speckle2graph/models/logical.py
speckle2graph/neo4j_queries/__init__.py
speckle2graph/neo4j_queries/basic_queries.py
speckle2graph/neo4j_queries/label_makers.py
speckle2graph/traversers/__init__.py
speckle2graph/traversers/base_traverser.py
speckle2graph/traversers/property_extractors.py
speckle2graph/traversers/traverse_ifc_dag.py
speckle2graph/traversers/traverse_revit_dag.py
speckle2graph/utils/__init__.py
speckle2graph/utils/helpers.py
speckle2graph-0.0.5.dist-info/licenses/LICENSE
speckle2graph-0.0.5.dist-info/METADATA
speckle2graph-0.0.5.dist-info/WHEEL
speckle2graph-0.0.5.dist-info/top_level.txt
speckle2graph-0.0.5.dist-info/RECORD
