Metadata-Version: 2.4
Name: Speckle2Graph
Version: 0.0.5
Summary: Enable graph-based analysis of any Speckle model.
Author-email: Arsy <arseneyworking@gmail.com>
License: Apache
Requires-Python: >=3.10
License-File: LICENSE
Requires-Dist: specklepy>=3.1.0
Requires-Dist: numpy>=1.24.0
Requires-Dist: scipy>=1.10.0
Requires-Dist: trimesh>=4.0.0
Requires-Dist: python-fcl>=0.7.0
Requires-Dist: networkx>=3.0
Requires-Dist: rtree>=1.0.0
Requires-Dist: neo4j>=5.0.0
Requires-Dist: tqdm>=4.65.0
Requires-Dist: loguru>=0.7.0
Dynamic: license-file
